{
    "global": {
        "ask_for_confirmation_before_quitting": false,
        "show_in_menu_bar": false
    },
    "profiles": [
        {
            "complex_modifications": {
                "rules": [
                    {
                        "description": "Open battery health by capslock+1, world clock by capslock+2, quick calendar by capslock+3, kill process by capslock+4, activity monitor by capslock+5, storage by capslock+6, search repositories by capslock+7, weather by capslock+8(prerequisites:add the hotkey and install battery health, quick calendar, world clock, github, kill process, weather in raycast)\nCapslock+shift->capslock",
                        "manipulators": [
                            {
                                "from": {
                                    "key_code": "caps_lock",
                                    "modifiers": { "optional": ["any"] }
                                },
                                "to": [
                                    {
                                        "set_variable": {
                                            "name": "caps_lock pressed",
                                            "value": 1
                                        }
                                    }
                                ],
                                "to_after_key_up": [
                                    {
                                        "set_variable": {
                                            "name": "caps_lock pressed",
                                            "value": 0
                                        }
                                    }
                                ],
                                "type": "basic"
                            },
                            {
                                "conditions": [
                                    {
                                        "name": "caps_lock pressed",
                                        "type": "variable_if",
                                        "value": 1
                                    }
                                ],
                                "from": {
                                    "key_code": "1",
                                    "modifiers": { "optional": ["any"] }
                                },
                                "to": {
                                    "key_code": "e",
                                    "modifiers": ["left_control", "left_command"]
                                },
                                "type": "basic"
                            },
                            {
                                "conditions": [
                                    {
                                        "name": "caps_lock pressed",
                                        "type": "variable_if",
                                        "value": 1
                                    }
                                ],
                                "from": {
                                    "key_code": "2",
                                    "modifiers": { "optional": ["any"] }
                                },
                                "to": {
                                    "key_code": "r",
                                    "modifiers": ["left_control", "left_command"]
                                },
                                "type": "basic"
                            },
                            {
                                "conditions": [
                                    {
                                        "name": "caps_lock pressed",
                                        "type": "variable_if",
                                        "value": 1
                                    }
                                ],
                                "from": {
                                    "key_code": "3",
                                    "modifiers": { "optional": ["any"] }
                                },
                                "to": {
                                    "key_code": "t",
                                    "modifiers": ["left_control", "left_command"]
                                },
                                "type": "basic"
                            },
                            {
                                "conditions": [
                                    {
                                        "name": "caps_lock pressed",
                                        "type": "variable_if",
                                        "value": 1
                                    }
                                ],
                                "from": {
                                    "key_code": "4",
                                    "modifiers": { "optional": ["any"] }
                                },
                                "to": {
                                    "key_code": "m",
                                    "modifiers": ["left_option", "left_command"]
                                },
                                "type": "basic"
                            },
                            {
                                "conditions": [
                                    {
                                        "name": "caps_lock pressed",
                                        "type": "variable_if",
                                        "value": 1
                                    }
                                ],
                                "from": {
                                    "key_code": "5",
                                    "modifiers": { "optional": ["any"] }
                                },
                                "to": { "shell_command": "open '/System/Applications/Utilities/Activity Monitor.app'" },
                                "type": "basic"
                            },
                            {
                                "conditions": [
                                    {
                                        "name": "caps_lock pressed",
                                        "type": "variable_if",
                                        "value": 1
                                    }
                                ],
                                "from": {
                                    "key_code": "6",
                                    "modifiers": { "optional": ["any"] }
                                },
                                "to": {
                                    "key_code": "w",
                                    "modifiers": ["left_control", "left_command"]
                                },
                                "type": "basic"
                            },
                            {
                                "conditions": [
                                    {
                                        "name": "caps_lock pressed",
                                        "type": "variable_if",
                                        "value": 1
                                    }
                                ],
                                "from": {
                                    "key_code": "7",
                                    "modifiers": { "optional": ["any"] }
                                },
                                "to": {
                                    "key_code": "k",
                                    "modifiers": ["left_option", "left_command"]
                                },
                                "type": "basic"
                            },
                            {
                                "conditions": [
                                    {
                                        "name": "caps_lock pressed",
                                        "type": "variable_if",
                                        "value": 1
                                    }
                                ],
                                "from": {
                                    "key_code": "8",
                                    "modifiers": { "optional": ["any"] }
                                },
                                "to": {
                                    "key_code": "n",
                                    "modifiers": ["left_option", "left_command"]
                                },
                                "type": "basic"
                            },
                            {
                                "conditions": [
                                    {
                                        "name": "caps_lock pressed",
                                        "type": "variable_if",
                                        "value": 1
                                    }
                                ],
                                "from": {
                                    "key_code": "left_shift",
                                    "modifiers": { "optional": ["any"] }
                                },
                                "to": { "key_code": "caps_lock" },
                                "type": "basic"
                            }
                        ]
                    },
                    {
                        "description": "Open visual studio code by function key(f5), iterm by function key(f6)",
                        "manipulators": [
                            {
                                "from": {
                                    "key_code": "f5",
                                    "modifiers": { "optional": ["any"] }
                                },
                                "to": { "shell_command": "open '/Applications/Visual Studio Code.app'" },
                                "type": "basic"
                            },
                            {
                                "from": {
                                    "key_code": "f6",
                                    "modifiers": { "optional": ["any"] }
                                },
                                "to": { "shell_command": "open '/Applications/iTerm.app'" },
                                "type": "basic"
                            }
                        ]
                    },
                    {
                        "description": "Show desktop by function key(f7)(prerequisite:add show desktop shortcut in settings)",
                        "manipulators": [
                            {
                                "from": {
                                    "key_code": "f7",
                                    "modifiers": { "optional": ["any"] }
                                },
                                "to": { "key_code": "f19" },
                                "type": "basic"
                            }
                        ]
                    },
                    {
                        "description": "Open download folder by function key(f8), root folder by function key(f9)",
                        "manipulators": [
                            {
                                "from": {
                                    "key_code": "f8",
                                    "modifiers": { "optional": ["any"] }
                                },
                                "to": { "shell_command": "open '/Users/timoptimothy/Downloads'" },
                                "type": "basic"
                            },
                            {
                                "from": {
                                    "key_code": "f9",
                                    "modifiers": { "optional": ["any"] }
                                },
                                "to": { "shell_command": "open '/Users/timoptimothy'" },
                                "type": "basic"
                            }
                        ]
                    }
                ]
            },
            "fn_function_keys": [
                {
                    "from": { "key_code": "f4" },
                    "to": [{ "apple_vendor_keyboard_key_code": "launchpad" }]
                },
                {
                    "from": { "key_code": "f5" },
                    "to": [{ "key_code": "vk_none" }]
                },
                {
                    "from": { "key_code": "f6" },
                    "to": [{ "key_code": "vk_none" }]
                },
                {
                    "from": { "key_code": "f7" },
                    "to": [{ "key_code": "vk_none" }]
                },
                {
                    "from": { "key_code": "f8" },
                    "to": [{ "key_code": "vk_none" }]
                },
                {
                    "from": { "key_code": "f9" },
                    "to": [{ "key_code": "vk_none" }]
                },
                {
                    "from": { "key_code": "f10" },
                    "to": [{ "consumer_key_code": "fast_forward" }]
                }
            ],
            "name": "Default profile",
            "selected": true,
            "virtual_hid_keyboard": { "keyboard_type_v2": "ansi" }
        }
    ]
}